ethereum/__init__.py
ethereum/ethash.py
ethereum/exceptions.py
ethereum/fork_criteria.py
ethereum/genesis.py
ethereum/py.typed
ethereum/trace.py
ethereum/assets/cache_sizes_2048_epochs.json
ethereum/assets/dataset_sizes_2048_epochs.json
ethereum/assets/mainnet.json
ethereum/assets/blocks/block_1.json
ethereum/assets/blocks/block_1234567.json
ethereum/assets/blocks/block_12964999.json
ethereum/crypto/__init__.py
ethereum/crypto/blake2.py
ethereum/crypto/elliptic_curve.py
ethereum/crypto/hash.py
ethereum/crypto/kzg.py
ethereum/forks/arrow_glacier/__init__.py
ethereum/forks/arrow_glacier/blocks.py
ethereum/forks/arrow_glacier/bloom.py
ethereum/forks/arrow_glacier/exceptions.py
ethereum/forks/arrow_glacier/fork.py
ethereum/forks/arrow_glacier/fork_types.py
ethereum/forks/arrow_glacier/state.py
ethereum/forks/arrow_glacier/transactions.py
ethereum/forks/arrow_glacier/trie.py
ethereum/forks/arrow_glacier/utils/__init__.py
ethereum/forks/arrow_glacier/utils/address.py
ethereum/forks/arrow_glacier/utils/hexadecimal.py
ethereum/forks/arrow_glacier/utils/message.py
ethereum/forks/arrow_glacier/vm/__init__.py
ethereum/forks/arrow_glacier/vm/exceptions.py
ethereum/forks/arrow_glacier/vm/gas.py
ethereum/forks/arrow_glacier/vm/interpreter.py
ethereum/forks/arrow_glacier/vm/memory.py
ethereum/forks/arrow_glacier/vm/runtime.py
ethereum/forks/arrow_glacier/vm/stack.py
ethereum/forks/arrow_glacier/vm/instructions/__init__.py
ethereum/forks/arrow_glacier/vm/instructions/arithmetic.py
ethereum/forks/arrow_glacier/vm/instructions/bitwise.py
ethereum/forks/arrow_glacier/vm/instructions/block.py
ethereum/forks/arrow_glacier/vm/instructions/comparison.py
ethereum/forks/arrow_glacier/vm/instructions/control_flow.py
ethereum/forks/arrow_glacier/vm/instructions/environment.py
ethereum/forks/arrow_glacier/vm/instructions/keccak.py
ethereum/forks/arrow_glacier/vm/instructions/log.py
ethereum/forks/arrow_glacier/vm/instructions/memory.py
ethereum/forks/arrow_glacier/vm/instructions/stack.py
ethereum_execution-2.19.0.dist-info/licenses/LICENSE.md
ethereum_execution-2.19.0.dist-info/METADATA
ethereum_execution-2.19.0.dist-info/WHEEL
ethereum_execution-2.19.0.dist-info/entry_points.txt
ethereum_execution-2.19.0.dist-info/top_level.txt
ethereum_execution-2.19.0.dist-info/RECORD
