Metadata-Version: 2.4
Name: ethereum-execution
Version: 2.19.0
Summary: Ethereum execution layer specification, provided as a Python package for tooling and testing
License-Expression: CC0-1.0
Project-URL: Homepage, https://github.com/ethereum/execution-specs
Classifier: Programming Language :: Python :: 3
Classifier: Programming Language :: Python :: 3.11
Classifier: Programming Language :: Python :: Implementation :: PyPy
Classifier: Programming Language :: Python :: Implementation :: CPython
Classifier: Intended Audience :: Developers
Classifier: Natural Language :: English
Requires-Python: >=3.11
License-File: LICENSE.md
Requires-Dist: pycryptodome<4,>=3.22
Requires-Dist: coincurve<21,>=20
Requires-Dist: typing_extensions>=4.4
Requires-Dist: py-ecc<9,>=8.0.0b2
Requires-Dist: ethereum-types<0.3,>=0.2.4
Requires-Dist: ethereum-rlp<0.2,>=0.1.4
Requires-Dist: cryptography<46,>=45.0.1
Requires-Dist: platformdirs<5,>=4.2
Requires-Dist: libcst<2,>=1.8
Provides-Extra: optimized
Requires-Dist: rust-pyspec-glue<0.1.0,>=0.0.9; extra == "optimized"
Requires-Dist: ethash<2,>=1.1.0; extra == "optimized"
Dynamic: license-file
